{
  "quarry": {
    "cached": {
      "famineTs": "9223372036854775807",
      "index": 1,
      "lastUpdateTs": "1645170428",
      "numMiners": "2",
      "rewardsPerTokenStored": "0",
      "rewardsShare": "0",
      "totalTokensDeposited": "751297881421"
    },
    "index": 1,
    "quarry": "8hxDDtzUTjPD53YN8vtp6qpLc9MJSxzgsqrabGrPn7wN",
    "slug": "1",
    "stakedToken": {
      "decimals": 6,
      "mint": "3wt5jcreZVFLVHvSaESGKvPy8DNeYD1sv4LLxJhJVfaL"
    }
  },
  "rewarder": {
    "authority": "Ci8TyJztU2jPNRikzCvZcCo3iCr6ffqLGR3HQ9j3xbcZ",
    "mintWrapper": "BmzqWGYAq4UZkzUr8CpTS9EX7UXTaEqusf1kkApwitWr",
    "rewardsToken": {
      "decimals": -1,
      "mint": "7xkHEF7qsPRUsKDT7akjLq9pBoLxnygMPRH72xqQxfL2"
    }
  },
  "stakedToken": null,
  "underlyingTokens": []
}