{
  "quarry": {
    "cached": {
      "famineTs": "9223372036854775807",
      "index": 0,
      "lastUpdateTs": "0",
      "numMiners": "2",
      "rewardsPerTokenStored": "0",
      "rewardsShare": "0",
      "totalTokensDeposited": "0"
    },
    "index": 0,
    "quarry": "F8KwQ2NTb85UcRcAVpHniauEYUfMP8t5pF8CwVjjwDDS",
    "slug": "0",
    "stakedToken": {
      "decimals": 6,
      "mint": "ApQfa9bbVab8pzFdk394uvecTSNEvkfvDTmcYL6tqHiZ"
    }
  },
  "rewarder": {
    "authority": "7z1s6fY1wX5FNT4CkgPibVRXW5YTcnSZcb68RVE8HEQf",
    "mintWrapper": "Hmq7mCsR8MSWBM1mco4CoUNcMVcL42mp893dgLXTXa3Y",
    "rewardsToken": {
      "decimals": -1,
      "mint": "1jmL9RoVFxn3smLdY8dbAh159xqWYQxLhp7Q39rnDdj"
    }
  },
  "stakedToken": null,
  "underlyingTokens": []
}