{
  "authority": "41jB9dMz2zVuwZ8JZthaumXFSN3AqYCobqSWduciU5UQ",
  "mintWrapper": "Cht7NKDbesdktczyCWcwgZ3tuiZRFVhQjJGFSoN98rdg",
  "quarries": [
    {
      "cached": {
        "famineTs": "9223372036854775807",
        "index": 0,
        "lastUpdateTs": "0",
        "numMiners": "1",
        "rewardsPerTokenStored": "0",
        "rewardsShare": "0",
        "totalTokensDeposited": "0"
      },
      "index": 0,
      "quarry": "Bq7LMgaeGQXV8vacVNSTAiCtDx5Eqq1n3j5hMaKVRBFU",
      "slug": "0",
      "stakedToken": {
        "decimals": 6,
        "mint": "BwXekv4c25bUff4oX4ZuJxa8hTDRwoQG4E6u3sUajgyz"
      }
    },
    {
      "cached": {
        "famineTs": "9223372036854775807",
        "index": 1,
        "lastUpdateTs": "0",
        "numMiners": "1",
        "rewardsPerTokenStored": "0",
        "rewardsShare": "0",
        "totalTokensDeposited": "0"
      },
      "index": 1,
      "quarry": "51VJsBv5R24Gb3XHAf1QWqe8AgnyrjvZ6s5DBMSSokeU",
      "slug": "1",
      "stakedToken": {
        "decimals": 6,
        "mint": "6GhapojRQkbZfwcX7jWAcph8afT6ZN3CkJ9Bc4PWsJLu"
      }
    }
  ],
  "rewardsToken": {
    "decimals": -1,
    "mint": "9CB6Sbxd1KVffZr2N2b66YHZ7BGMw92MzEfXtvVdKEMw"
  }
}