{
  "authority": "3icnwpLyUFEihFmETN6nzRXE8Spn8HAtuc35jVcKuPae",
  "mintWrapper": "HJsXaWZ2DPAWJN9HugFTJjJ3auCmTugjMVKsCNF8SjDg",
  "quarries": [
    {
      "cached": {
        "famineTs": "9223372036854775807",
        "index": 0,
        "lastUpdateTs": "1640958740",
        "numMiners": "2",
        "rewardsPerTokenStored": "75021153330150079672",
        "rewardsShare": "1",
        "totalTokensDeposited": "0"
      },
      "index": 0,
      "quarry": "HB8fGxYC9fuWJuZvap7kKpNaaS1tqugVvvoimADMet7v",
      "slug": "0",
      "stakedToken": {
        "decimals": 6,
        "mint": "Ck9t5PgHSxm3TAcwHB7Ncw1HvGGRwRehdWLzSanUtxzJ"
      }
    },
    {
      "cached": {
        "famineTs": "9223372036854775807",
        "index": 1,
        "lastUpdateTs": "1645571921",
        "numMiners": "5",
        "rewardsPerTokenStored": "949069957815300077141",
        "rewardsShare": "1",
        "totalTokensDeposited": "700556"
      },
      "index": 1,
      "quarry": "BR3JRSfVUJ6Dub6gsRRBzFeeTVubzzwAj3YyaxqzwSMP",
      "slug": "1",
      "stakedToken": {
        "decimals": 6,
        "mint": "4jL2htQtstTzatmtJL85M6z89E238ozg5eUa9u54Qyxb"
      }
    }
  ],
  "rewardsToken": {
    "decimals": -1,
    "mint": "BRZLJRECJwRk6v1KtQscMoRK4BtcgFyo2wCHo9sMYhfn"
  }
}