{
  "quarry": {
    "cached": {
      "famineTs": "9223372036854775807",
      "index": 0,
      "lastUpdateTs": "0",
      "numMiners": "1",
      "rewardsPerTokenStored": "0",
      "rewardsShare": "0",
      "totalTokensDeposited": "0"
    },
    "index": 0,
    "quarry": "5TaKHaXfX5xkFguDcHxHCXc7s7w2D2LS4MKZLxXLVY73",
    "slug": "8nsij",
    "stakedToken": {
      "decimals": 6,
      "mint": "8NSiJkqJeKSX34HCdnT8souSCsNZgpGNVvRRQwKezWgT"
    }
  },
  "stakedToken": null,
  "underlyingTokens": []
}