{
  "quarry": {
    "cached": {
      "famineTs": "9223372036854775807",
      "index": 1,
      "lastUpdateTs": "1645645390",
      "numMiners": "35",
      "rewardsPerTokenStored": "0",
      "rewardsShare": "0",
      "totalTokensDeposited": "15832117137"
    },
    "index": 1,
    "quarry": "6mznU9AU52QvVYnLXKT5WR47EgRxsimKjdsY3fJ21tjh",
    "slug": "1",
    "stakedToken": {
      "decimals": 6,
      "mint": "HzAeigSdnrPY1VcHNidaJE4CE7M9drsubTeuGRRwdNcb"
    }
  },
  "stakedToken": null,
  "underlyingTokens": []
}