{
  "authority": "6jmBNuXPX9FvAMSX1HZi3EkxuyRb9vGmwyCoX4eVh3qz",
  "mintWrapper": "GVtygEvQRRxXCbeNEwVHkCzdt8jswr7T2gYLNtJnhGHo",
  "quarries": [
    {
      "cached": {
        "famineTs": "9223372036854775807",
        "index": 0,
        "lastUpdateTs": "1647201035",
        "numMiners": "1278",
        "rewardsPerTokenStored": "8447549223829751996439",
        "rewardsShare": "0",
        "totalTokensDeposited": "2756297395768"
      },
      "index": 0,
      "quarry": "9bPMa5dzJ44UGnkx4st2apPJNxb1h5DT2XbzqBh7ELUZ",
      "slug": "qrcash-usdc",
      "stakedToken": {
        "decimals": 6,
        "mint": "HoiqP8QaE1bvikWrRjrvcWL2v2AjYtnwKrveu2vNReMy"
      }
    },
    {
      "cached": {
        "famineTs": "9223372036854775807",
        "index": 1,
        "lastUpdateTs": "1647099828",
        "numMiners": "167",
        "rewardsPerTokenStored": "15727710460469878604866",
        "rewardsShare": "0",
        "totalTokensDeposited": "472645211510"
      },
      "index": 1,
      "quarry": "CgiCrf6uVZgvovSgiFYSPqginW2xgfMxBU418zr8D8pn",
      "slug": "qrpai-cash",
      "stakedToken": {
        "decimals": 6,
        "mint": "AXMC4QhPZfx9kfMaYwwsn5WeEFivM7UnYw2tnVrD2xrA"
      }
    },
    {
      "cached": {
        "famineTs": "9223372036854775807",
        "index": 2,
        "lastUpdateTs": "1647201197",
        "numMiners": "857",
        "rewardsPerTokenStored": "3069942778581281036927",
        "rewardsShare": "295999947051",
        "totalTokensDeposited": "13371926485569"
      },
      "index": 2,
      "quarry": "E2zqjr8DsAXotspX5Eays37w9vnZaCWPokbaSnSfpf9n",
      "slug": "qrust-cash",
      "stakedToken": {
        "decimals": 6,
        "mint": "HdSp5C6F4GvVUhCD7hqWaj74cm4fVU2NZXs3r7jzCSVe"
      }
    },
    {
      "cached": {
        "famineTs": "9223372036854775807",
        "index": 3,
        "lastUpdateTs": "1647191444",
        "numMiners": "234",
        "rewardsPerTokenStored": "24339471468238647748",
        "rewardsShare": "16015376827575512",
        "totalTokensDeposited": "2636429801259517"
      },
      "index": 3,
      "quarry": "BUNETXgxVog7yV5pHjxAN9Pgms6zwLRdprRt31r5Ei5x",
      "slug": "qracusd-cash",
      "stakedToken": {
        "decimals": 9,
        "mint": "6YSGgj2cbTYc75V6qXBqiAWrHfdoSH4TbqHvN7fANSyj"
      }
    },
    {
      "cached": {
        "famineTs": "9223372036854775807",
        "index": 4,
        "lastUpdateTs": "1647017925",
        "numMiners": "162",
        "rewardsPerTokenStored": "81577897944699922499553",
        "rewardsShare": "0",
        "totalTokensDeposited": "16074591212"
      },
      "index": 4,
      "quarry": "8ZQdi83kJHNSr8zYma432AXbXtqYNVJYGCo3d2iZ4GSF",
      "slug": "sasol-cash",
      "stakedToken": {
        "decimals": 9,
        "mint": "jXWR3mBofnAU1Gv4URvYTu3Yedkv7JZA8zHJzxXdzeA"
      }
    },
    {
      "cached": {
        "famineTs": "9223372036854775807",
        "index": 5,
        "lastUpdateTs": "1647204901",
        "numMiners": "1091",
        "rewardsPerTokenStored": "3046853612240325826356",
        "rewardsShare": "2765017790945435",
        "totalTokensDeposited": "16981997426055"
      },
      "index": 5,
      "quarry": "4Fc2ztbSF64YRWYtaeN9cvgjpgnzvTmJ3Sp3DW1DNsHT",
      "slug": "scash-cow",
      "stakedToken": {
        "decimals": 6,
        "mint": "J8Le9FqYK12xadDw3Mm8k37rWj4tLtHZaWs65fgFjf4F"
      }
    },
    {
      "cached": {
        "famineTs": "9223372036854775807",
        "index": 6,
        "lastUpdateTs": "1647017925",
        "numMiners": "136",
        "rewardsPerTokenStored": "215568114126922419932861",
        "rewardsShare": "0",
        "totalTokensDeposited": "607988767"
      },
      "index": 6,
      "quarry": "GGF2LWTFfyEGLgCzMF8KBTdzvZEUynwPruZTV54XukTZ",
      "slug": "scash-luna",
      "stakedToken": {
        "decimals": 6,
        "mint": "4CsomP6td9X9rQM3RiXa2E8vwinpRU7hVGhTToWjj6fe"
      }
    },
    {
      "cached": {
        "famineTs": "9223372036854775807",
        "index": 7,
        "lastUpdateTs": "1647192205",
        "numMiners": "75",
        "rewardsPerTokenStored": "939780320090172824698372",
        "rewardsShare": "1532419696922985",
        "totalTokensDeposited": "26346792861"
      },
      "index": 7,
      "quarry": "AAqRP5aC1CYqH9bfPVTjLxSLj72NY75bWch3LLfQJHTm",
      "slug": "prt-cash",
      "stakedToken": {
        "decimals": 2,
        "mint": "EoNJJWQMdvMscCL7V6wNrGaDLi791sPZH1hSzHcwfsDj"
      }
    },
    {
      "cached": {
        "famineTs": "9223372036854775807",
        "index": 8,
        "lastUpdateTs": "1647161497",
        "numMiners": "30",
        "rewardsPerTokenStored": "990802335298103353164107",
        "rewardsShare": "704138144502577",
        "totalTokensDeposited": "4404410360"
      },
      "index": 8,
      "quarry": "CpxUJPQibBjUXLhXzzvN3F2mARzBiSEgKPNa8D2tMQ2a",
      "slug": "port-cash",
      "stakedToken": {
        "decimals": 2,
        "mint": "DHvEBPxbUbDr53DZtr7tJ1Wm1S1UQGe67ZN6Ciyv7tHW"
      }
    },
    {
      "cached": {
        "famineTs": "9223372036854775807",
        "index": 9,
        "lastUpdateTs": "1647193041",
        "numMiners": "132",
        "rewardsPerTokenStored": "985757128209646893482304",
        "rewardsShare": "3507637445670680",
        "totalTokensDeposited": "16532555068"
      },
      "index": 9,
      "quarry": "9uN6j3CL7aYNHbCvSg919NaEXSp6KJcTakZ5fQi9daaU",
      "slug": "pole-cash",
      "stakedToken": {
        "decimals": 2,
        "mint": "Gwr9C41tv51oAjD1gqzpsLP1sGJ4KRTvQCLtaaWi72YD"
      }
    },
    {
      "cached": {
        "famineTs": "9223372036854775807",
        "index": 10,
        "lastUpdateTs": "1647196634",
        "numMiners": "208",
        "rewardsPerTokenStored": "808012530026325655733715",
        "rewardsShare": "4609799125262868",
        "totalTokensDeposited": "84380227678"
      },
      "index": 10,
      "quarry": "BGLr39pyujk68LMNnS4tKd4FXfHAamytbazmE375Bgmo",
      "slug": "c98-cash",
      "stakedToken": {
        "decimals": 2,
        "mint": "4g7DwZVn8edcSYR34zE4Dm13YLH6ZvtXCNnaUyQSFy9w"
      }
    },
    {
      "cached": {
        "famineTs": "9223372036854775807",
        "index": 11,
        "lastUpdateTs": "1647151032",
        "numMiners": "11",
        "rewardsPerTokenStored": "1993118507680028236044155",
        "rewardsShare": "56614847720810",
        "totalTokensDeposited": "386966898"
      },
      "index": 11,
      "quarry": "5wHd1JFqXeTmSUUtB3FYT3YbgnnfEV2ENuYubbr2CTZm",
      "slug": "step-cash",
      "stakedToken": {
        "decimals": 2,
        "mint": "BteRTgfrrxyVwJAgAvv9GsLuyn4CWdBRYbBBqE3FM94z"
      }
    },
    {
      "cached": {
        "famineTs": "9223372036854775807",
        "index": 12,
        "lastUpdateTs": "1647017925",
        "numMiners": "7",
        "rewardsPerTokenStored": "6185564304626944824835849",
        "rewardsShare": "3774323181387",
        "totalTokensDeposited": "26928149"
      },
      "index": 12,
      "quarry": "ExixRSzwjERXH1tbNzSc4J5AN98FUNGeY6P3KWG1Hz8r",
      "slug": "1sol-cash",
      "stakedToken": {
        "decimals": 2,
        "mint": "2kxbv7aSt3ieDXPwTBc6SM9DwwxY9WtLqu5WRf2ZTYq8"
      }
    },
    {
      "cached": {
        "famineTs": "9223372036854775807",
        "index": 13,
        "lastUpdateTs": "1647017925",
        "numMiners": "15",
        "rewardsPerTokenStored": "3157691070234817379492511",
        "rewardsShare": "3774323181387",
        "totalTokensDeposited": "311259620"
      },
      "index": 13,
      "quarry": "szXLFzhDyhG7UCrVDQWDbFGQrkzM7aN9zJJYezD6tsq",
      "slug": "dfl-cash",
      "stakedToken": {
        "decimals": 2,
        "mint": "bcyfFCjEnHA9NXGm35Zb3bwSeiz4kpw7W1TvFwbQHa6"
      }
    },
    {
      "cached": {
        "famineTs": "9223372036854775807",
        "index": 14,
        "lastUpdateTs": "1647017925",
        "numMiners": "8",
        "rewardsPerTokenStored": "488322279384683938958449",
        "rewardsShare": "7548646362774",
        "totalTokensDeposited": "1262253956"
      },
      "index": 14,
      "quarry": "ApFwaYgDg1k5CNPU7ZCv4FZ8PZ9YmWgX7x3XEudbBB1B",
      "slug": "sonar-cash",
      "stakedToken": {
        "decimals": 2,
        "mint": "5csZtCiN3Rap6vk8xwoj8bhHb1rwzdXDtrAkKq1TGRp4"
      }
    },
    {
      "cached": {
        "famineTs": "9223372036854775807",
        "index": 15,
        "lastUpdateTs": "1647017925",
        "numMiners": "9",
        "rewardsPerTokenStored": "357548974095927890504853",
        "rewardsShare": "9787988070181",
        "totalTokensDeposited": "1461710485"
      },
      "index": 15,
      "quarry": "FCah768kx2biJVUoxoptc4UHFsvMWihTz4tp5vNcD9sb",
      "slug": "sny-cash",
      "stakedToken": {
        "decimals": 2,
        "mint": "3EC7pn6pXDCm1BBuAXXwUUnhay6FVKZxHP7KZc1Z27nk"
      }
    },
    {
      "cached": {
        "famineTs": "9223372036854775807",
        "index": 16,
        "lastUpdateTs": "1647174890",
        "numMiners": "10",
        "rewardsPerTokenStored": "339674623090787973982354",
        "rewardsShare": "7548646362774",
        "totalTokensDeposited": "1438998060"
      },
      "index": 16,
      "quarry": "7gGH6ajHvrahPAqzGLr6HejUXMmbEagm9VuCWZUqpU6m",
      "slug": "abr-cash",
      "stakedToken": {
        "decimals": 2,
        "mint": "CPNCsU7FCtPnvfBcMSRBq1jixVCPY4eMjGfYTqXRnv3s"
      }
    },
    {
      "cached": {
        "famineTs": "9223372036854775807",
        "index": 17,
        "lastUpdateTs": "1647017925",
        "numMiners": "4",
        "rewardsPerTokenStored": "652227340414898055536873",
        "rewardsShare": "7548646362774",
        "totalTokensDeposited": "1085206063"
      },
      "index": 17,
      "quarry": "4gpaec4TovwRWLVuEeg7V3FaZ2EC1FEZLx8XMRqizQpJ",
      "slug": "in-cash",
      "stakedToken": {
        "decimals": 2,
        "mint": "GWAoMkDgnJbdUPphm76ZMmkm8KJvpqrde2ctXgfy1byD"
      }
    },
    {
      "cached": {
        "famineTs": "9223372036854775807",
        "index": 18,
        "lastUpdateTs": "1647035329",
        "numMiners": "105",
        "rewardsPerTokenStored": "68432051461215263657227",
        "rewardsShare": "157335902874885",
        "totalTokensDeposited": "2515386635"
      },
      "index": 18,
      "quarry": "4tssPMzeW59KKi2o1dxMqxnv8tid4X7fHkWxpuSXaenm",
      "slug": "mix-cash",
      "stakedToken": {
        "decimals": 2,
        "mint": "Ey8M9ZK6bqzXCSuvJFMaQMFNgWShn6aCahTvL1nbcFyk"
      }
    },
    {
      "cached": {
        "famineTs": "9223372036854775807",
        "index": 19,
        "lastUpdateTs": "1647017925",
        "numMiners": "5",
        "rewardsPerTokenStored": "898381233539398349106700",
        "rewardsShare": "7548646362774",
        "totalTokensDeposited": "130907786"
      },
      "index": 19,
      "quarry": "E6JNDjasQL7wnNU9LwNxgvge81PHjNZXHkX6aXvMQRuL",
      "slug": "bot-cash",
      "stakedToken": {
        "decimals": 2,
        "mint": "Cyggmjx7iWios6jqrYRbZwFE3AYaqV5UfyVyYF5XgCYU"
      }
    },
    {
      "cached": {
        "famineTs": "9223372036854775807",
        "index": 20,
        "lastUpdateTs": "1647017925",
        "numMiners": "8",
        "rewardsPerTokenStored": "4958830018400592184473958",
        "rewardsShare": "7548646362774",
        "totalTokensDeposited": "9829941"
      },
      "index": 20,
      "quarry": "GaMtV3AAYTRzcUMDJb4bk9aP5Ski8goW94TT87AyF3zc",
      "slug": "god-cash",
      "stakedToken": {
        "decimals": 2,
        "mint": "813D4afWKgjHfc65LiPtF1rodNreuJ6ZQH4tMhuFrX2k"
      }
    },
    {
      "cached": {
        "famineTs": "9223372036854775807",
        "index": 21,
        "lastUpdateTs": "1647151032",
        "numMiners": "5",
        "rewardsPerTokenStored": "226485955686808362234271",
        "rewardsShare": "9624257498513",
        "totalTokensDeposited": "1651569684"
      },
      "index": 21,
      "quarry": "DFgEnKvvXiV9FESnKaexnHQiYozQkxGQEq8hRoG1uaxf",
      "slug": "ivn-cash",
      "stakedToken": {
        "decimals": 2,
        "mint": "BqZEnXNMQWJS81Ps5NnSofh24d3ffwJWwwP2ZrKpNjcZ"
      }
    },
    {
      "cached": {
        "famineTs": "9223372036854775807",
        "index": 22,
        "lastUpdateTs": "1647017925",
        "numMiners": "9",
        "rewardsPerTokenStored": "283933041619081019369623",
        "rewardsShare": "140051873779115",
        "totalTokensDeposited": "6120946970"
      },
      "index": 22,
      "quarry": "BwD3KchAHqBP9rbq7pjYbqb7ZFrY5AtWjqW6DwSZeBQf",
      "slug": "cope-cash",
      "stakedToken": {
        "decimals": 2,
        "mint": "HwXQWncukjBwExBsYFofcuf5nLLvgfsg3tRLfpH7fh7G"
      }
    },
    {
      "cached": {
        "famineTs": "9223372036854775807",
        "index": 23,
        "lastUpdateTs": "1647151038",
        "numMiners": "121",
        "rewardsPerTokenStored": "15012873542657180674775",
        "rewardsShare": "204072644348529",
        "totalTokensDeposited": "199451149310"
      },
      "index": 23,
      "quarry": "5wXkztartAFDdy76UrUixxqvZoQrAhaLdMBdPmAxEUbj",
      "slug": "ssunny-cash",
      "stakedToken": {
        "decimals": 6,
        "mint": "BzZRM9HciRcgWNCjF1UdiYnHiNx6YAjuzcinVFL9CKYw"
      }
    },
    {
      "cached": {
        "famineTs": "9223372036854775807",
        "index": 24,
        "lastUpdateTs": "1647177192",
        "numMiners": "106",
        "rewardsPerTokenStored": "122202076924339256832",
        "rewardsShare": "9062516595216",
        "totalTokensDeposited": "9667661045385"
      },
      "index": 24,
      "quarry": "4ecVJePyhYL17pmjd6vySUrPL8tFnCRMB1xRGVREt4FU",
      "slug": "scash-oogi",
      "stakedToken": {
        "decimals": 9,
        "mint": "9qCyVjDUq5Jh76a5KAVtz8BXxj8fNcXjnDf4yLe5zdAa"
      }
    }
  ],
  "rewardsToken": {
    "decimals": 6,
    "mint": "CowKesoLUaHSbAMaUxJUj7eodHHsaLsS65cy8NFyRDGP"
  },
  "rewardsTokenInfo": {
    "address": "CowKesoLUaHSbAMaUxJUj7eodHHsaLsS65cy8NFyRDGP",
    "chainId": 101,
    "decimals": 6,
    "extensions": {
      "discord": "https://discord.com/invite/GmkRRKJkuh",
      "medium": "https://medium.com/@cashioapp",
      "twitter": "https://twitter.com/CashioApp",
      "website": "https://cashio.app"
    },
    "logoURI": "https://raw.githubusercontent.com/cashioapp/cashio-token-list/main/assets/cow.png",
    "name": "Cash Cow",
    "symbol": "COW",
    "tags": [
      "governance-token"
    ]
  }
}