{
  "quarry": {
    "cached": {
      "famineTs": "9223372036854775807",
      "index": 1,
      "lastUpdateTs": "0",
      "numMiners": "1",
      "rewardsPerTokenStored": "0",
      "rewardsShare": "0",
      "totalTokensDeposited": "0"
    },
    "index": 1,
    "quarry": "7ot6xS6xbaCYsokiVMaH5yFuMiSCrX5QArfWC5jTZYyh",
    "slug": "1",
    "stakedToken": {
      "decimals": 6,
      "mint": "4Phc25xqiJbHgLr9na6VS4izjgemAVmL9Y68FMTfJzmm"
    }
  },
  "rewarder": {
    "authority": "3nNmXisQ1HevJvDM3ZnCmrooKc3rXPuYuosjJ2cRuah6",
    "mintWrapper": "EAJkazXuWB1DyQ1UUufqUx2wRpCyiu5Smx1w9pVt3Jzk",
    "rewardsToken": {
      "decimals": -1,
      "mint": "4Z7a6gFfjW1PuFdDoV6zowdQB7nuymvv6eipio3d26uT"
    }
  },
  "stakedToken": null,
  "underlyingTokens": []
}