{
  "authority": "Ap64cJfNW7S3gD6QNQczzdCReWcWv4JSSw8Lya7FS2Mj",
  "mintWrapper": "6T5p5kpG9V6LWne373jcVegcrV3bTLffQWaLKgeT6FJk",
  "quarries": [
    {
      "cached": {
        "famineTs": "9223372036854775807",
        "index": 0,
        "lastUpdateTs": "1642436711",
        "numMiners": "2",
        "rewardsPerTokenStored": "0",
        "rewardsShare": "0",
        "totalTokensDeposited": "1484983"
      },
      "index": 0,
      "quarry": "3EdaRRD5sgGCT1unqHd9PhGgcbV2Do7FPo3gcXQ9edJj",
      "slug": "g45an",
      "stakedToken": {
        "decimals": 6,
        "mint": "G45anEegV6HMi3gPs2fAPLmMxtRzQ4re7vL6abpaqaQb"
      }
    },
    {
      "cached": {
        "famineTs": "9223372036854775807",
        "index": 1,
        "lastUpdateTs": "1642436711",
        "numMiners": "2",
        "rewardsPerTokenStored": "0",
        "rewardsShare": "0",
        "totalTokensDeposited": "595996"
      },
      "index": 1,
      "quarry": "HbTf24nrja4M8Yw98VjWqS3sZUVEY3Aq5z4KVPpXF5U5",
      "slug": "2e9ez",
      "stakedToken": {
        "decimals": 6,
        "mint": "2e9EZw6oUQ9cttwopLngF6gHG9KnJW1x8kCstSZrKAzX"
      }
    }
  ],
  "rewardsToken": {
    "decimals": 6,
    "mint": "BbWQz1bA7e12yDnTNR5UeW4tPhq7cqv9Hb7hANvbDBVs"
  }
}