{
  "quarry": {
    "cached": {
      "famineTs": "9223372036854775807",
      "index": 1,
      "lastUpdateTs": "0",
      "numMiners": "1",
      "rewardsPerTokenStored": "0",
      "rewardsShare": "0",
      "totalTokensDeposited": "0"
    },
    "index": 1,
    "quarry": "5rpEkispus1dFtgsyXsDLRmpqMbvovKwLe32kan5E93u",
    "slug": "1",
    "stakedToken": {
      "decimals": 6,
      "mint": "CUSrbpirxQ5ncYAEKzcfWTABBBJVXino9mMeVeY5KHxW"
    }
  },
  "rewarder": {
    "authority": "J5CG95xo8PY3GPqN5giaymGCUY3ACGJRun672hyXmtJY",
    "mintWrapper": "4469Uzp1vXU3eJA8TKuqSWBXby85Av8CL6FimfAibcdf",
    "rewardsToken": {
      "decimals": -1,
      "mint": "J4WvxjE8KEstWKCdjXaneiJm6jce1Ffh412RjmLMExhM"
    }
  },
  "stakedToken": null,
  "underlyingTokens": []
}