{
  "authority": "Fe4qVMmGaY1MC5TChz42g71jY1MSjGUauB1t4oTK8un1",
  "mintWrapper": "6GJ7o6h9CJtMoMmbGHFeth88aaZfsHN4HVytJAz9CYGV",
  "quarries": [
    {
      "cached": {
        "famineTs": "9223372036854775807",
        "index": 0,
        "lastUpdateTs": "1639458501",
        "numMiners": "1",
        "rewardsPerTokenStored": "0",
        "rewardsShare": "0",
        "totalTokensDeposited": "23928479"
      },
      "index": 0,
      "quarry": "NTRTCSNfiCM31aQwTQoyMsagAbNefo3c4JYQdmc4frx",
      "stakedToken": {
        "decimals": 6,
        "mint": "2CxGxw1PQdopdMJpNke3qr5GGsxWtFPgZ17mvcnefNhy"
      }
    },
    {
      "cached": {
        "famineTs": "9223372036854775807",
        "index": 1,
        "lastUpdateTs": "1639458501",
        "numMiners": "1",
        "rewardsPerTokenStored": "0",
        "rewardsShare": "0",
        "totalTokensDeposited": "8971754"
      },
      "index": 1,
      "quarry": "Ah5LQaLjJEu6XmR2wza3bvUEgHTDWTujX8od4oZPNTLd",
      "stakedToken": {
        "decimals": 6,
        "mint": "BB6fKBjWpiffw16oTjcf3PXeS8ZcBP6BbXNQ1Y5Gtcsv"
      }
    }
  ],
  "rewardsToken": {
    "decimals": 6,
    "mint": "7zhFEi5gryFcW8zC5KHcTtMQ2REYMLac8X6szxtjmC4z"
  }
}