{
  "quarry": {
    "cached": {
      "famineTs": "9223372036854775807",
      "index": 1,
      "lastUpdateTs": "0",
      "numMiners": "1",
      "rewardsPerTokenStored": "0",
      "rewardsShare": "0",
      "totalTokensDeposited": "0"
    },
    "index": 1,
    "quarry": "CwJ8okJPDEtabJNvw5TRZrSveAyMuNwHbwt4rzucvdqK",
    "slug": "1",
    "stakedToken": {
      "decimals": 6,
      "mint": "EJ8akWBC466cCXH5hb6MYJx5XmVdGrqvF1xvhRBQ94S"
    }
  },
  "stakedToken": null,
  "underlyingTokens": []
}