{
  "quarry": {
    "cached": {
      "famineTs": "9223372036854775807",
      "index": 0,
      "lastUpdateTs": "1639652980",
      "numMiners": "1",
      "rewardsPerTokenStored": "0",
      "rewardsShare": "0",
      "totalTokensDeposited": "23928479"
    },
    "index": 0,
    "quarry": "7WWpuZECh619qnm1bXDpc7BW6DE8SyWc6gpiWGiZKsFw",
    "slug": "0",
    "stakedToken": {
      "decimals": 6,
      "mint": "B4NzdvNG6L4nKoG4ondcd3KMKkDwYdZYZQ6RWtEdTdtd"
    }
  },
  "rewarder": {
    "authority": "6LUwF6RTtKeAiTwrjCg3rkELeJXhP5TtRWgKkirMnZ5z",
    "mintWrapper": "2hoyM4FKrwD4XQWhksfb7YjbF7GPrVq2cpdZevXAy1Ze",
    "rewardsToken": {
      "decimals": -1,
      "mint": "rYhijTDB9R6QGUzQiQeaU7jxZ8RUzjN9ngxrJigdn1B"
    }
  },
  "stakedToken": null,
  "underlyingTokens": []
}