{
  "authority": "4YXUXwE8QuKLfiMDeHZLTtyU6b3z7k2o7vDA2WnAj7tk",
  "mintWrapper": "5MxaFqKHQHZA1dyfzGwrHBdgMoPMR5MhF2KpSP54zyxx",
  "quarries": [
    {
      "cached": {
        "famineTs": "9223372036854775807",
        "index": 0,
        "lastUpdateTs": "0",
        "numMiners": "1",
        "rewardsPerTokenStored": "0",
        "rewardsShare": "0",
        "totalTokensDeposited": "0"
      },
      "index": 0,
      "quarry": "Bi2eGabNEWtexiznbcCrazA9FbHPLpPXAFC2C1yVD2k2",
      "slug": "0",
      "stakedToken": {
        "decimals": 6,
        "mint": "RAYww2hfJy2JTmw3quH9stn42Ko9gFufiQx3EMTyeuV"
      }
    },
    {
      "cached": {
        "famineTs": "9223372036854775807",
        "index": 1,
        "lastUpdateTs": "0",
        "numMiners": "1",
        "rewardsPerTokenStored": "0",
        "rewardsShare": "0",
        "totalTokensDeposited": "0"
      },
      "index": 1,
      "quarry": "2HoJaxoJZEN6whJ9Rqws97kWVqGUHU17CUTBQkDxBiux",
      "slug": "1",
      "stakedToken": {
        "decimals": 6,
        "mint": "55qdC9fjV8LrdirB4eaxpK2iE7nmeLNJ9gV8PvpFCuGY"
      }
    }
  ],
  "rewardsToken": {
    "decimals": -1,
    "mint": "DayG3rYYUSwYiBSFhFSiW6Tmy3qqELBAiFj1RiH5bmwn"
  }
}