{
  "authority": "DZSWq2PgWfBbZbhYdubNNq1z6iyKDh1BbckwMRDHr2Gv",
  "mintWrapper": "8GB9iivKqNpGbGS2BtXHaeNNzMTzWcNnGDerhh9b9gJ2",
  "quarries": [
    {
      "cached": {
        "famineTs": "9223372036854775807",
        "index": 0,
        "lastUpdateTs": "1642002351",
        "numMiners": "2",
        "rewardsPerTokenStored": "0",
        "rewardsShare": "0",
        "totalTokensDeposited": "47804118"
      },
      "index": 0,
      "quarry": "3p41DFd6GDfsdMc5tNJHGkhtnCMTiMnqCo2pC2cqPLzY",
      "stakedToken": {
        "decimals": 6,
        "mint": "D3Z8vf4NdnLjrg7e7Y6WDLs4m5TzEgssUmwnYTNokuui"
      }
    },
    {
      "cached": {
        "famineTs": "9223372036854775807",
        "index": 1,
        "lastUpdateTs": "1642002351",
        "numMiners": "2",
        "rewardsPerTokenStored": "0",
        "rewardsShare": "0",
        "totalTokensDeposited": "19123043"
      },
      "index": 1,
      "quarry": "EFDJAGJmCMzww9xP9b6a6ws4vhmyyJ8m9vsuoR2LxAhE",
      "stakedToken": {
        "decimals": 6,
        "mint": "CS9oWdptXoUWjWw7x6jPewWSt5kmGk2JkS8JrEMhXH5d"
      }
    }
  ],
  "rewardsToken": {
    "decimals": 6,
    "mint": "AG87SZA6y7JgsXA1yhNU1yhDdYpwyR3weNYzjVUSg5Zd"
  }
}