{
  "quarry": {
    "cached": {
      "famineTs": "9223372036854775807",
      "index": 0,
      "lastUpdateTs": "1639549935",
      "numMiners": "1",
      "rewardsPerTokenStored": "0",
      "rewardsShare": "0",
      "totalTokensDeposited": "23928479"
    },
    "index": 0,
    "quarry": "HxtR1YXAuUMhYtG6y1dc8dTeCcbU1wD5VQ9XXBMWBeVa",
    "slug": "2ajgx",
    "stakedToken": {
      "decimals": 6,
      "mint": "2aJGXhvev6xqTcaGvTRGBKNxbQttFeuFiebW8nJpGdjJ"
    }
  },
  "stakedToken": null,
  "underlyingTokens": []
}