{
  "quarry": {
    "cached": {
      "famineTs": "9223372036854775807",
      "index": 1,
      "lastUpdateTs": "0",
      "numMiners": "1",
      "rewardsPerTokenStored": "0",
      "rewardsShare": "0",
      "totalTokensDeposited": "0"
    },
    "index": 1,
    "quarry": "5Spm3pFBDNiK7j5nSd9kiu1oRJPnqvDTYVb439mqqVXv",
    "slug": "1",
    "stakedToken": {
      "decimals": 6,
      "mint": "DyP2dvbupgNsMetF9iQ4vzDBfJmAfXUEwExh5zoZnCfc"
    }
  },
  "rewarder": {
    "authority": "6qkKdxcDNTkx7YHvSuNjaeiyDpeSb35m7C4Qt13HY5po",
    "mintWrapper": "Di6rFtG7Dy6E4yCMXHQj1m6EM3Am4aKDV2aWE8pckXVs",
    "rewardsToken": {
      "decimals": -1,
      "mint": "5sN6qxuPn2GKVZRXUXeqgYgHayRw1MDwTFbxGEARbtNy"
    }
  },
  "stakedToken": null,
  "underlyingTokens": []
}