{
  "quarry": {
    "cached": {
      "famineTs": "9223372036854775807",
      "index": 0,
      "lastUpdateTs": "1639663560",
      "numMiners": "1",
      "rewardsPerTokenStored": "0",
      "rewardsShare": "0",
      "totalTokensDeposited": "23928479"
    },
    "index": 0,
    "quarry": "2bkbnZqq1524QZXUu87PXWT9Ltkq3R8qHctqdnnmAfbs",
    "slug": "bniw5",
    "stakedToken": {
      "decimals": 6,
      "mint": "BniW5QKn3JD4Z5pw2ZWFo1Cz9tgz15u9RiWR5bPNBE2v"
    }
  },
  "stakedToken": null,
  "underlyingTokens": []
}