{
  "authority": "F4VFp4tFTyrQWo9YVjCbPE5eQP27ice2zyGDp2tN2Rkm",
  "mintWrapper": "8d1MnZe4UspHfsSvT9LnpkShWsP5y72433PEVhosahz9",
  "quarries": [
    {
      "cached": {
        "famineTs": "9223372036854775807",
        "index": 0,
        "lastUpdateTs": "0",
        "numMiners": "0",
        "rewardsPerTokenStored": "0",
        "rewardsShare": "0",
        "totalTokensDeposited": "0"
      },
      "index": 0,
      "quarry": "9bRcenxWY4B1sJp4eqi9VmPqLifhZ2fvh4m8UebN8vkt",
      "slug": "0",
      "stakedToken": {
        "decimals": 9,
        "mint": "vSoLBtUuQcP8qwV9QmGqPmrGsF8VAUQ5JnYPGsRwoMV"
      }
    },
    {
      "cached": {
        "famineTs": "9223372036854775807",
        "index": 1,
        "lastUpdateTs": "1711295906",
        "numMiners": "1",
        "rewardsPerTokenStored": "0",
        "rewardsShare": "0",
        "totalTokensDeposited": "75000000"
      },
      "index": 1,
      "quarry": "9njBn2z4y1z1GXJ2VD3eDA8b1Skm11yFdBcRdtqjiToL",
      "slug": "1",
      "stakedToken": {
        "decimals": 9,
        "mint": "vSoLxydx6akxyMD9XEcPvGYNGq6Nn66oqVb3UkGkei7"
      }
    }
  ],
  "rewardsToken": {
    "decimals": -1,
    "mint": "PTS5EXvvvhe5cLApf3oYy3XdVqTsDJKeGXvvxYJTYK3"
  }
}