{
  "authority": "F4VFp4tFTyrQWo9YVjCbPE5eQP27ice2zyGDp2tN2Rkm",
  "mintWrapper": "4Kf7FLWtEPPPcUpizxK82QYNoLSPd2fQTiVLSBx5oKqz",
  "quarries": [
    {
      "cached": {
        "famineTs": "9223372036854775807",
        "index": 0,
        "lastUpdateTs": "1716797538",
        "numMiners": "10",
        "rewardsPerTokenStored": "0",
        "rewardsShare": "0",
        "totalTokensDeposited": "62113026168"
      },
      "index": 0,
      "quarry": "BmfmJ6Y8xNZrswn9uzfsneVVb7xXPHKnAGWHtddFdcZg",
      "slug": "0",
      "stakedToken": {
        "decimals": 6,
        "mint": "vPtS4ywrbEuufwPkBXsCYkeTBfpzCd6hF52p8kJGt9b"
      }
    },
    {
      "cached": {
        "famineTs": "9223372036854775807",
        "index": 1,
        "lastUpdateTs": "1716794466",
        "numMiners": "113",
        "rewardsPerTokenStored": "410259303492180514316",
        "rewardsShare": "1",
        "totalTokensDeposited": "4941063357948"
      },
      "index": 1,
      "quarry": "56jUntrxMLEZ4d82GPvKkWr28CuaBQsFwWxzQEMoaWck",
      "slug": "qrvlpa8",
      "stakedToken": {
        "decimals": 9,
        "mint": "CDg82SVPf5FL2gy3RNkRzzsYjmrJoW7LzhqHL31rjB32"
      }
    },
    {
      "cached": {
        "famineTs": "9223372036854775807",
        "index": 2,
        "lastUpdateTs": "1716796510",
        "numMiners": "1420",
        "rewardsPerTokenStored": "250531934167116908763",
        "rewardsShare": "1",
        "totalTokensDeposited": "8889895129893"
      },
      "index": 2,
      "quarry": "3nH3FHZZTcjSfVf2efB4CQqnN7HJfgn3HaYMKSRiGRTM",
      "slug": "vsol",
      "stakedToken": {
        "decimals": 9,
        "mint": "vSoLxydx6akxyMD9XEcPvGYNGq6Nn66oqVb3UkGkei7"
      }
    }
  ],
  "rewardsToken": {
    "decimals": -1,
    "mint": "vPtS4ywrbEuufwPkBXsCYkeTBfpzCd6hF52p8kJGt9b"
  }
}