{
  "quarry": {
    "cached": {
      "famineTs": "9223372036854775807",
      "index": 1,
      "lastUpdateTs": "0",
      "numMiners": "2",
      "rewardsPerTokenStored": "0",
      "rewardsShare": "0",
      "totalTokensDeposited": "0"
    },
    "index": 1,
    "quarry": "7rCChCAC8t4dce5szvLBEBgHP85Pidb7HZknF2w1Ty4L",
    "slug": "g1crv",
    "stakedToken": {
      "decimals": 6,
      "mint": "G1CrVGJyty9uq4ij8HtTi7BXib72UWtv6d4PowMuzuSy"
    }
  },
  "stakedToken": null,
  "underlyingTokens": []
}