{
  "quarry": {
    "cached": {
      "famineTs": "9223372036854775807",
      "index": 1,
      "lastUpdateTs": "1641905141",
      "numMiners": "2",
      "rewardsPerTokenStored": "0",
      "rewardsShare": "0",
      "totalTokensDeposited": "19123043"
    },
    "index": 1,
    "quarry": "AZPk65J62j1YbpReCjYjSSJcApvX7cSYP7JZtZizFrhu",
    "slug": "ayypx",
    "stakedToken": {
      "decimals": 6,
      "mint": "AyYpxGgWLoiXeAsBVkzgzXYQZjqzmb5sFNeopVtRVgny"
    }
  },
  "stakedToken": null,
  "underlyingTokens": []
}