{
  "authority": "HYjY2XQNLUwDdRSYbPfdPADgYQFZ82Cir3yNvBSTtqjn",
  "mintWrapper": "9p5dDdPRS3QjKQ6NpsWWm92pVxEZKwm4WY3MHfVkqMz4",
  "quarries": [
    {
      "cached": {
        "famineTs": "9223372036854775807",
        "index": 0,
        "lastUpdateTs": "1669198735",
        "numMiners": "115",
        "rewardsPerTokenStored": "19019565382039829434",
        "rewardsShare": "500",
        "totalTokensDeposited": "785333104010"
      },
      "index": 0,
      "quarry": "C8GtpEKrvZ4CgvmaNMjxn3G5UUfd8Yf3LDGPct1pqCfu",
      "slug": "ec7o8",
      "stakedToken": {
        "decimals": 7,
        "mint": "EC7o8FssHyDwv5Abs2W3cjjpD7iXza14XVr5jNnKnZrs"
      }
    },
    {
      "cached": {
        "famineTs": "9223372036854775807",
        "index": 1,
        "lastUpdateTs": "1669158470",
        "numMiners": "45",
        "rewardsPerTokenStored": "5423115350144322999",
        "rewardsShare": "1500",
        "totalTokensDeposited": "1763993934560"
      },
      "index": 1,
      "quarry": "73KLjBaVepMd8ZDbUypuqmJnrAd3ChQ3kWLRg85pqqNi",
      "slug": "dcsre",
      "stakedToken": {
        "decimals": 7,
        "mint": "DcsrERrQEcD3opeR14ZzuhmeZQ6TreFnfYMtVFy1NJrb"
      }
    },
    {
      "cached": {
        "famineTs": "9223372036854775807",
        "index": 2,
        "lastUpdateTs": "1668994813",
        "numMiners": "8",
        "rewardsPerTokenStored": "7349217000169889995",
        "rewardsShare": "2500",
        "totalTokensDeposited": "2721569011040"
      },
      "index": 2,
      "quarry": "7frawc7P758qStR9UyPHc8Agx7PdvjbjnNia2kRejDci",
      "slug": "6d1zu",
      "stakedToken": {
        "decimals": 7,
        "mint": "6D1ZU9aE22iskCuyeZ9xCzspXoaLgfhW1Pc7fWqw7SkL"
      }
    },
    {
      "cached": {
        "famineTs": "9223372036854775807",
        "index": 3,
        "lastUpdateTs": "1669151174",
        "numMiners": "3",
        "rewardsPerTokenStored": "10579636947274449566",
        "rewardsShare": "5500",
        "totalTokensDeposited": "4584036856440"
      },
      "index": 3,
      "quarry": "D9Ki75C8b4k9vajBk7XiQwZEzXDq9tjTwyimzd8Hdc6R",
      "slug": "cc56e",
      "stakedToken": {
        "decimals": 7,
        "mint": "Cc56EW8CnYCWyWkwG7jmSXSDjrwekdrPgjXdqpvFk21V"
      }
    }
  ],
  "rewardsToken": {
    "decimals": 7,
    "mint": "G3ywJe259j51Jqwj29ZQXS9GmkrazyPs2yv8VRp9xfPt"
  },
  "rewardsTokenInfo": {
    "address": "G3ywJe259j51Jqwj29ZQXS9GmkrazyPs2yv8VRp9xfPt",
    "chainId": 101,
    "decimals": 7,
    "name": "Token G3yw",
    "symbol": "G3ywJ"
  }
}