{
  "quarry": {
    "cached": {
      "famineTs": "9223372036854775807",
      "index": 0,
      "lastUpdateTs": "0",
      "numMiners": "2",
      "rewardsPerTokenStored": "0",
      "rewardsShare": "0",
      "totalTokensDeposited": "0"
    },
    "index": 0,
    "quarry": "219F5tY4pcwwkEgWcJ16hw13XmJZarv5ctWYL2MfGpvg",
    "stakedToken": {
      "decimals": 6,
      "mint": "DJ6XKHShE5oRsjYEAzybgA5XjW9rF2TaQVetGoFRVkwy"
    }
  },
  "slug": "0",
  "stakedToken": null,
  "underlyingTokens": []
}