{
  "authority": "AToqdMt53fwwkfCL7V46phHCEmEikHmCtxQQyDq6tAoJ",
  "mintWrapper": "4YjgRRypySm4U4etRAKzCGPGgprgX7Jn2uXd1uftubg9",
  "quarries": [
    {
      "cached": {
        "famineTs": "9223372036854775807",
        "index": 0,
        "lastUpdateTs": "0",
        "numMiners": "2",
        "rewardsPerTokenStored": "0",
        "rewardsShare": "0",
        "totalTokensDeposited": "0"
      },
      "index": 0,
      "quarry": "EGdgmTmKsHR6MKtbGBgTa6GACXmc2vCTMYPnzsuUWeou",
      "slug": "0",
      "stakedToken": {
        "decimals": 6,
        "mint": "Gqu8p1BDi72Ufgv6J8BoyCXf7FktNfiYDYGFgFHtTvij"
      }
    },
    {
      "cached": {
        "famineTs": "9223372036854775807",
        "index": 1,
        "lastUpdateTs": "0",
        "numMiners": "2",
        "rewardsPerTokenStored": "0",
        "rewardsShare": "0",
        "totalTokensDeposited": "0"
      },
      "index": 1,
      "quarry": "3Y72kDqQwaNej17DLbf6grUf8PzGmTD611kPNd1R1phN",
      "slug": "1",
      "stakedToken": {
        "decimals": 6,
        "mint": "JANDMRkQc8edVFVwbZTiei6YMNWyCHkDQwXZxMx7HxSY"
      }
    }
  ],
  "rewardsToken": {
    "decimals": -1,
    "mint": "AGv8U74Mn4GZpDLK553yudJTyQWTqhDy5spDNasddQzc"
  }
}