{
  "authority": "93AkNAkeeoxS3ci6kbXPYTwuh9ZmHgGWWdyE7eE5DGAv",
  "mintWrapper": "oxKfQx2K3ytFNyB8ZrTorrQoaDHs89Eaax8WQ8BeDbz",
  "quarries": [
    {
      "cached": {
        "famineTs": "9223372036854775807",
        "index": 0,
        "lastUpdateTs": "0",
        "numMiners": "1",
        "rewardsPerTokenStored": "0",
        "rewardsShare": "0",
        "totalTokensDeposited": "0"
      },
      "index": 0,
      "quarry": "WjXuVr1ZGQLktFMbUsVBHe2hjJ4gbELjo3nkg23tQgo",
      "stakedToken": {
        "decimals": 6,
        "mint": "rmXtFZwJPmTrjmE5fLXjX3PuxWeBd8XHbAgQDkayKMZ"
      }
    },
    {
      "cached": {
        "famineTs": "9223372036854775807",
        "index": 1,
        "lastUpdateTs": "0",
        "numMiners": "1",
        "rewardsPerTokenStored": "0",
        "rewardsShare": "0",
        "totalTokensDeposited": "0"
      },
      "index": 1,
      "quarry": "Fj56VvwF2SGbEBDimdWJqukZvd1sAKy5yS7csnQq8JER",
      "stakedToken": {
        "decimals": 6,
        "mint": "HuNeRAcynccFBLsUuBqpmdSuGt2nkSJ8oDM6ae6Lfm3W"
      }
    }
  ],
  "rewardsToken": {
    "decimals": 6,
    "mint": "8ocfVbwLoTAL9UmkTk5ZHwfXC5qRj7PmEA81hWw2VvfJ"
  }
}