{
  "quarry": {
    "cached": {
      "famineTs": "9223372036854775807",
      "index": 1,
      "lastUpdateTs": "0",
      "numMiners": "1",
      "rewardsPerTokenStored": "0",
      "rewardsShare": "0",
      "totalTokensDeposited": "0"
    },
    "index": 1,
    "quarry": "2LydjKgRdzFoJoBmAoEW9Wkn64XJ8vUaVGpxUbPQo3os",
    "slug": "1",
    "stakedToken": {
      "decimals": 6,
      "mint": "AW8izXRknSSRjsxnPhZyMuEYb25sJ59kD2XpFpJ653zm"
    }
  },
  "stakedToken": null,
  "underlyingTokens": []
}