{
  "authority": "FJGxSGftLEADHaAr5MC9UXV8hsWAEporizioYskdYDAP",
  "mintWrapper": "Dr8rHjh96B8KqDiBGwu4w58DUpiCsrTo45sjmXqHAbL9",
  "quarries": [
    {
      "cached": {
        "famineTs": "1654103848",
        "index": 0,
        "lastUpdateTs": "1654103848",
        "numMiners": "1",
        "rewardsPerTokenStored": "5124095576030",
        "rewardsShare": "100",
        "totalTokensDeposited": "1000000000"
      },
      "index": 0,
      "quarry": "2wnid2Drb6hXjGupgZhufvGHpcPsRSb1upqJKbcq3Foy",
      "slug": "0",
      "stakedToken": {
        "decimals": 6,
        "mint": "ESPEH7NXCh3epCneDrcge1a2cAQugqT8vaX5EvkuqKeq"
      }
    }
  ],
  "rewardsToken": {
    "decimals": -1,
    "mint": "E2NLp4M7cDLTpstAHcJawYDmekqUXFdBzBZMtnTscbGT"
  }
}