{
  "quarry": {
    "cached": {
      "famineTs": "9223372036854775807",
      "index": 0,
      "lastUpdateTs": "1645256226",
      "numMiners": "2",
      "rewardsPerTokenStored": "0",
      "rewardsShare": "0",
      "totalTokensDeposited": "0"
    },
    "index": 0,
    "quarry": "2AEveKtygnMh8dnf3fbz5mdJHqDFeBgNq7KHe9wR2xXU",
    "slug": "0",
    "stakedToken": {
      "decimals": 6,
      "mint": "5ENLnaTeKp1ufpWcLvV8GSKrRexFfWz1oDXELMcEWrB2"
    }
  },
  "rewarder": {
    "authority": "3NGXaszoJAgF3q8HJk9zqWSLuH1ftnDMjwpjLYAp5XPG",
    "mintWrapper": "iQ72zKYUJYSx35R98UdrmsFYgKARmBxEvPvhHbmQMTZ",
    "rewardsToken": {
      "decimals": -1,
      "mint": "3LRE58zYHgUovpaVfFA1SYCYwjapSucB1SWYUmAECpfJ"
    }
  },
  "stakedToken": null,
  "underlyingTokens": []
}