{
  "quarry": {
    "cached": {
      "famineTs": "9223372036854775807",
      "index": 0,
      "lastUpdateTs": "1635608483",
      "numMiners": "2",
      "rewardsPerTokenStored": "0",
      "rewardsShare": "1",
      "totalTokensDeposited": "0"
    },
    "index": 0,
    "quarry": "BqXWmKoKBctRqN9Yas63ZWHyAz3zyV7pCM125TJfynxC",
    "slug": "0",
    "stakedToken": {
      "decimals": 9,
      "mint": "FebMuhkkhx61MhzfYYLfr3dXJwUf441kUK6W1hnzxUKh"
    }
  },
  "stakedToken": null,
  "underlyingTokens": []
}