{
  "authority": "G8HtnKUYpciQUVScBVrBAjmHBD6a9V2Y44oHguCKuABi",
  "mintWrapper": "85SdYcTg1zXrkaw4A8HdBJsoUQzAjwWmAnDF3PYarWAm",
  "quarries": [
    {
      "cached": {
        "famineTs": "9223372036854775807",
        "index": 0,
        "lastUpdateTs": "0",
        "numMiners": "1",
        "rewardsPerTokenStored": "0",
        "rewardsShare": "0",
        "totalTokensDeposited": "0"
      },
      "index": 0,
      "quarry": "4Jr6TnShCkeCy61kwxQr9b1NTydU7FFkMXxZqJep3v8e",
      "slug": "bdeb8",
      "stakedToken": {
        "decimals": 6,
        "mint": "BDeb8EgQkmbcqCTMc73u69SALw1TincF9BT3s1dDRUJy"
      }
    },
    {
      "cached": {
        "famineTs": "9223372036854775807",
        "index": 1,
        "lastUpdateTs": "0",
        "numMiners": "1",
        "rewardsPerTokenStored": "0",
        "rewardsShare": "0",
        "totalTokensDeposited": "0"
      },
      "index": 1,
      "quarry": "65QyL4iibbMC6c6FKE9qetJxCyHM9ex7sYaHBAVyTSuQ",
      "slug": "3dcbt",
      "stakedToken": {
        "decimals": 6,
        "mint": "3DCbTGGZKBYQe3oes7jNGwfLvY4gM1F1kuEqUsWYi4bQ"
      }
    }
  ],
  "rewardsToken": {
    "decimals": 6,
    "mint": "GKTDcoyTEnVUZXaPwXyU3QhpjtnZTMmvCY5vmGchJ2Ub"
  }
}