{
  "quarry": {
    "cached": {
      "famineTs": "9223372036854775807",
      "index": 0,
      "lastUpdateTs": "0",
      "numMiners": "1",
      "rewardsPerTokenStored": "0",
      "rewardsShare": "0",
      "totalTokensDeposited": "0"
    },
    "index": 0,
    "quarry": "9T2V9Gmejy4wPC9KLYXZ3GrdE9yseziL4L1G5wPsP5UV",
    "slug": "0",
    "stakedToken": {
      "decimals": 6,
      "mint": "ESiHxPcaxaaTU14kUBYXLsoCzmxGBjSefiZVvAcogPkY"
    }
  },
  "rewarder": {
    "authority": "6swW12CpCdD48dgpMydP8kkCQdHHBKndQpTBFUFeYb6F",
    "mintWrapper": "AUWtjajqDqbNGk2VH96A7m29hLWKbZPdtfi896PYjuJ9",
    "rewardsToken": {
      "decimals": -1,
      "mint": "AZMqcpPXLrmX5Arq8SikeYVU1DNJYhg4Nx6CZbeUj54k"
    }
  },
  "stakedToken": null,
  "underlyingTokens": []
}