{
  "authority": "GXPrbrnpjZFCivZj3pqPcwS9iBx2om68rXWySf9mEhHD",
  "mintWrapper": "4fYcqFqHdfz9Lie234YKyfPQkb5gpFgrcv9Zxyc3UPsR",
  "quarries": [
    {
      "cached": {
        "famineTs": "9223372036854775807",
        "index": 0,
        "lastUpdateTs": "0",
        "numMiners": "1",
        "rewardsPerTokenStored": "0",
        "rewardsShare": "0",
        "totalTokensDeposited": "0"
      },
      "index": 0,
      "quarry": "DbdqU3FQuAxwXbqS5WNSaTypmE4moGaEYhbSVhZCFUmH",
      "slug": 0,
      "stakedToken": {
        "decimals": 6,
        "mint": "82ij8X6jJD9ptkpVuV1ayQMzwpDkX1qcwwbHPxc3dG1w"
      }
    },
    {
      "cached": {
        "famineTs": "9223372036854775807",
        "index": 1,
        "lastUpdateTs": "0",
        "numMiners": "1",
        "rewardsPerTokenStored": "0",
        "rewardsShare": "0",
        "totalTokensDeposited": "0"
      },
      "index": 1,
      "quarry": "3sQn3g1pv6CBLSVQun8jKPHqzorq4vtXYpauWQqPUZCm",
      "slug": 1,
      "stakedToken": {
        "decimals": 6,
        "mint": "822AZAnETJYw8VQgzdj5SehMFssLZZqzXHbbeNcXT9uC"
      }
    }
  ],
  "rewardsToken": {
    "decimals": -1,
    "mint": "CHpiNd2WdKbFv2TSTrGfu2mqNFJGxi5BFTixx7evJXmM"
  }
}