{
  "quarry": {
    "cached": {
      "famineTs": "9223372036854775807",
      "index": 0,
      "lastUpdateTs": "1640004096",
      "numMiners": "1",
      "rewardsPerTokenStored": "0",
      "rewardsShare": "0",
      "totalTokensDeposited": "95597214"
    },
    "index": 0,
    "quarry": "GriaKMbnfQc3NzvT89pS8AWWmeXZR2kSryw8CHz2Fuyi",
    "slug": "0",
    "stakedToken": {
      "decimals": 6,
      "mint": "CVvpkVfVVKZEmrwvvyKKqBKqzRW8jkgx1DE3WDwhL9ib"
    }
  },
  "rewarder": {
    "authority": "6ioPM4pXftXyZv6h5hg2AJRD83UDXoBe3CvPUi3ReMbQ",
    "mintWrapper": "GQXonAi3ozTXbVhSU6gHHj7qrNGv2gi5X6VxFyN8Fvre",
    "rewardsToken": {
      "decimals": -1,
      "mint": "5QeDFUWVhSyEEtAuTqwofM39d9Mmqb1g2N4q632jReZD"
    }
  },
  "stakedToken": null,
  "underlyingTokens": []
}