{
  "authority": "FjpwNTkqk84ohP5CZBkvcxYhnvzFeWpmamBwg7Zf25Mr",
  "mintWrapper": "erGdiERj93oRbhvxdpCMhpxC3KwJjFFzX4YbtafBaGc",
  "quarries": [
    {
      "cached": {
        "famineTs": "9223372036854775807",
        "index": 0,
        "lastUpdateTs": "0",
        "numMiners": "1",
        "rewardsPerTokenStored": "0",
        "rewardsShare": "0",
        "totalTokensDeposited": "0"
      },
      "index": 0,
      "quarry": "3Uh35zEBztHzZA9szxF3vgxDvzviygYRsA3D3npQv9H1",
      "slug": 0,
      "stakedToken": {
        "decimals": 6,
        "mint": "6Uf7HSidUr5eUPfMwXBFGGfmEgVQuWwj69r9LKNKY6P4"
      }
    },
    {
      "cached": {
        "famineTs": "9223372036854775807",
        "index": 1,
        "lastUpdateTs": "0",
        "numMiners": "1",
        "rewardsPerTokenStored": "0",
        "rewardsShare": "0",
        "totalTokensDeposited": "0"
      },
      "index": 1,
      "quarry": "HdpDKQZiWNKXRKQk33rD2v6YJpS334ZtJiiqqUnuzuYn",
      "slug": 1,
      "stakedToken": {
        "decimals": 6,
        "mint": "3N2XUccqWq9e9h3h5S2rffVCEqVAkurBv2EAzhJzCTVr"
      }
    }
  ],
  "rewardsToken": {
    "decimals": -1,
    "mint": "97tr9iPP3UPz6Yj4n49YPBn2kZPgk4mzHwbQveEAErkv"
  }
}