{
  "quarry": {
    "cached": {
      "famineTs": "9223372036854775807",
      "index": 0,
      "lastUpdateTs": "1644899649",
      "numMiners": "2",
      "rewardsPerTokenStored": "0",
      "rewardsShare": "0",
      "totalTokensDeposited": "47126677535"
    },
    "index": 0,
    "quarry": "EwJNCJvh7KrUJbMzfsj11Jtf5cunUNhCRLjPggjJKrjh",
    "slug": "0",
    "stakedToken": {
      "decimals": 6,
      "mint": "CrfnVNc6uBta8WMJDUWycS6cfRCVHKDLqJmcsCtPAAtu"
    }
  },
  "stakedToken": null,
  "underlyingTokens": []
}