{
  "quarry": {
    "cached": {
      "famineTs": "9223372036854775807",
      "index": 0,
      "lastUpdateTs": "1642778155",
      "numMiners": "2",
      "rewardsPerTokenStored": "0",
      "rewardsShare": "0",
      "totalTokensDeposited": "1484983"
    },
    "index": 0,
    "quarry": "D9i5kd5pKTdWrAYMmPAGg6kfXqt96yVG2Z5BZGfNMVep",
    "slug": "0",
    "stakedToken": {
      "decimals": 6,
      "mint": "HdGR9Amw1WY34n9vZZCS6ou2MsGCwHQuBLut2hYUhqvg"
    }
  },
  "rewarder": {
    "authority": "eJKPDjUh9ZbfPRzhkDyC7p9iLiWbzazqZrk9tdyNoQN",
    "mintWrapper": "EuXYVngXKukrZ63LKh4o4N1k35dzLgRwvUd9eHPRJiS5",
    "rewardsToken": {
      "decimals": -1,
      "mint": "3KQ8uCrJEEcmpoeehm22r39nXBBeKf8FKcgA4ydh1ByE"
    }
  },
  "stakedToken": null,
  "underlyingTokens": []
}