{
  "authority": "69aV9GaGMQSZLHM2rQSRAPfDBkUTU8AXxvFdUBk7Syxv",
  "mintWrapper": "FBZFkHRE4mGVckeMNYeSAWXTFVKDPCnZo74mahijVQR2",
  "quarries": [
    {
      "cached": {
        "famineTs": "9223372036854775807",
        "index": 0,
        "lastUpdateTs": "1647590844",
        "numMiners": "831",
        "rewardsPerTokenStored": "14326607260790439",
        "rewardsShare": "100",
        "totalTokensDeposited": "10192525522990"
      },
      "index": 0,
      "quarry": "H5X3fTtypufVaPtH8D7GbMffCqSRHA3MWNj3FT4tVXQU",
      "slug": "qrust-cash",
      "stakedToken": {
        "decimals": 6,
        "mint": "HdSp5C6F4GvVUhCD7hqWaj74cm4fVU2NZXs3r7jzCSVe"
      }
    },
    {
      "cached": {
        "famineTs": "9223372036854775807",
        "index": 1,
        "lastUpdateTs": "1647590002",
        "numMiners": "201",
        "rewardsPerTokenStored": "11431677790683",
        "rewardsShare": "100",
        "totalTokensDeposited": "1011231815435871"
      },
      "index": 1,
      "quarry": "48n63dcqQ3zX1rinAksYu42J4aSpJbte3Mt6bNCnymio",
      "slug": "qrfrax-ust",
      "stakedToken": {
        "decimals": 8,
        "mint": "GqLcJdCkLgk5AsJ2gBadYpPRNHxoYFWpwb7csJ2ED176"
      }
    }
  ],
  "rewardsToken": {
    "decimals": -1,
    "mint": "LUN9joXyojPTbKf3HwcHw12PKMLrmzEMrUSAinUGKr5"
  }
}