{
  "quarry": {
    "cached": {
      "famineTs": "9223372036854775807",
      "index": 2,
      "lastUpdateTs": "1645078350",
      "numMiners": "615",
      "rewardsPerTokenStored": "934542679271295858",
      "rewardsShare": "1000",
      "totalTokensDeposited": "1382273027709349"
    },
    "index": 2,
    "quarry": "CeE8rNxCFx2RAgpS7trsmcTz7ydyun33wbNY7r2nEvPi",
    "slug": "renbtc-wbtc",
    "stakedToken": {
      "decimals": 8,
      "mint": "bLpASoWNdsz5DsjCaxpbM2FrkMowTJCydpwiDP4Vdzm"
    }
  },
  "rewarder": {
    "authority": "GdW7Accmjusk8qKUPoCMJasEje63h97igqkjdEpacpRN",
    "mintWrapper": "EVVDA3ZiAjTizemLGXNUN3gb6cffQFEYkFjFZokPmUPz",
    "rewardsToken": {
      "decimals": -1,
      "mint": "iouQcQBAiEXe6cKLS85zmZxUqaCqBdeHFpqKoSz615u"
    }
  },
  "stakedToken": null,
  "underlyingTokens": []
}