{
  "quarry": {
    "cached": {
      "famineTs": "9223372036854775807",
      "index": 1,
      "lastUpdateTs": "0",
      "numMiners": "2",
      "rewardsPerTokenStored": "0",
      "rewardsShare": "0",
      "totalTokensDeposited": "0"
    },
    "index": 1,
    "quarry": "7PKF4Eq2QTYFJhy9qfL7ZUon1iz1v1seyPDV3EVDs83c",
    "slug": "1",
    "stakedToken": {
      "decimals": 6,
      "mint": "3Z7w2eTGFXhA3t7YfcHdm8ZM31MUiNhTeYu79TpFPSJw"
    }
  },
  "rewarder": {
    "authority": "6qc6JeZSY5SeLiTHLT38HYg5PpEHaGZp4MrD96Z7mLZr",
    "mintWrapper": "5fCtC3AjMaToDUUHNzN5XxZdixY1TajfeaLiybH2EQpV",
    "rewardsToken": {
      "decimals": -1,
      "mint": "2oJB9gxxywdUEDAUFEtynMRSk6iEHuhPs7145y4qE14N"
    }
  },
  "stakedToken": null,
  "underlyingTokens": []
}