{
  "quarry": {
    "cached": {
      "famineTs": "9223372036854775807",
      "index": 0,
      "lastUpdateTs": "1641293473",
      "numMiners": "2",
      "rewardsPerTokenStored": "0",
      "rewardsShare": "0",
      "totalTokensDeposited": "0"
    },
    "index": 0,
    "quarry": "HAjmq5muN7heVryuJoVLdmy2buydfhdMoWvYqTQ74AkK",
    "slug": "0",
    "stakedToken": {
      "decimals": 6,
      "mint": "3KBBt53cdxnbC2rDM4YDaaYkaj5V9aotsMk81Kgn162c"
    }
  },
  "stakedToken": null,
  "underlyingTokens": []
}