{
  "authority": "7TcntF4TRVgJahzf8keiF3DGvzYnh9yFSbkkz45Huxrm",
  "mintWrapper": "Hy1pZAtwqmWn52uzhB6te26EwCtHorkqrSrD4X6Aaq9k",
  "quarries": [
    {
      "cached": {
        "famineTs": "9223372036854775807",
        "index": 0,
        "lastUpdateTs": "1649633450",
        "numMiners": "2",
        "rewardsPerTokenStored": "0",
        "rewardsShare": "0",
        "totalTokensDeposited": "29201493443053"
      },
      "index": 0,
      "quarry": "DWZVJDFsGBshMHhfxDY3igbWMDnCDw8aVksEHkmCMSdg",
      "slug": "8kbaf",
      "stakedToken": {
        "decimals": 6,
        "mint": "8KBAf8Y59Y1tc88bDkdwj8wQr2U9tM9dJVBTgSqxJbCq"
      }
    },
    {
      "cached": {
        "famineTs": "9223372036854775807",
        "index": 1,
        "lastUpdateTs": "1649633455",
        "numMiners": "2",
        "rewardsPerTokenStored": "0",
        "rewardsShare": "0",
        "totalTokensDeposited": "19497532490957"
      },
      "index": 1,
      "quarry": "5QYWhYdPyU1b1zYywVgK8DUZGGfg6Vn4gSskFLTNiDtd",
      "slug": "3vext",
      "stakedToken": {
        "decimals": 6,
        "mint": "3VExt6jduSjh5jVmAj2wPPxUvVv3xjJBZGj9VycH4NJa"
      }
    }
  ],
  "rewardsToken": {
    "decimals": 6,
    "mint": "Q6aBonw1NWoDXsxSYkFbevpEtAfCkdSCHCJ8ueaaUh4"
  },
  "rewardsTokenInfo": {
    "address": "Q6aBonw1NWoDXsxSYkFbevpEtAfCkdSCHCJ8ueaaUh4",
    "chainId": 103,
    "decimals": 6,
    "name": "Token Q6aB",
    "symbol": "Q6aBo"
  }
}